cliven-0.2.1.dist-info/licenses/LICENSE
main/__init__.py
main/chat.py
main/cliven.py
cliven-0.2.1.dist-info/METADATA
cliven-0.2.1.dist-info/WHEEL
cliven-0.2.1.dist-info/entry_points.txt
cliven-0.2.1.dist-info/top_level.txt
cliven-0.2.1.dist-info/RECORD
